iso_standards/__init__.py
iso_standards/base.py
iso_standards/errors.py
iso_standards/iso3166/__init__.py
iso_standards/iso3166/iso3166_1.py
iso_standards/iso3166/iso3166_2/AD.py
iso_standards/iso3166/iso3166_2/AE.py
iso_standards/iso3166/iso3166_2/AF.py
iso_standards/iso3166/iso3166_2/AG.py
iso_standards/iso3166/iso3166_2/AL.py
iso_standards/iso3166/iso3166_2/AM.py
iso_standards/iso3166/iso3166_2/AO.py
iso_standards/iso3166/iso3166_2/AR.py
iso_standards/iso3166/iso3166_2/AT.py
iso_standards/iso3166/iso3166_2/AU.py
iso_standards/iso3166/iso3166_2/AZ.py
iso_standards/iso3166/iso3166_2/BA.py
iso_standards/iso3166/iso3166_2/BB.py
iso_standards/iso3166/iso3166_2/BD.py
iso_standards/iso3166/iso3166_2/BE.py
iso_standards/iso3166/iso3166_2/BF.py
iso_standards/iso3166/iso3166_2/BG.py
iso_standards/iso3166/iso3166_2/BH.py
iso_standards/iso3166/iso3166_2/BI.py
iso_standards/iso3166/iso3166_2/BJ.py
iso_standards/iso3166/iso3166_2/BN.py
iso_standards/iso3166/iso3166_2/BO.py
iso_standards/iso3166/iso3166_2/BQ.py
iso_standards/iso3166/iso3166_2/BR.py
iso_standards/iso3166/iso3166_2/BS.py
iso_standards/iso3166/iso3166_2/BT.py
iso_standards/iso3166/iso3166_2/BW.py
iso_standards/iso3166/iso3166_2/BY.py
iso_standards/iso3166/iso3166_2/BZ.py
iso_standards/iso3166/iso3166_2/CA.py
iso_standards/iso3166/iso3166_2/CD.py
iso_standards/iso3166/iso3166_2/CF.py
iso_standards/iso3166/iso3166_2/CG.py
iso_standards/iso3166/iso3166_2/CH.py
iso_standards/iso3166/iso3166_2/CI.py
iso_standards/iso3166/iso3166_2/CL.py
iso_standards/iso3166/iso3166_2/CM.py
iso_standards/iso3166/iso3166_2/CN.py
iso_standards/iso3166/iso3166_2/CO.py
iso_standards/iso3166/iso3166_2/CR.py
iso_standards/iso3166/iso3166_2/CU.py
iso_standards/iso3166/iso3166_2/CV.py
iso_standards/iso3166/iso3166_2/CY.py
iso_standards/iso3166/iso3166_2/CZ.py
iso_standards/iso3166/iso3166_2/DE.py
iso_standards/iso3166/iso3166_2/DJ.py
iso_standards/iso3166/iso3166_2/DK.py
iso_standards/iso3166/iso3166_2/DM.py
iso_standards-0.1.3.dist-info/METADATA
iso_standards-0.1.3.dist-info/WHEEL
iso_standards-0.1.3.dist-info/RECORD
