Metadata-Version: 2.1
Name: iso-standards
Version: 0.1.3
Summary: ISO standards
License: MIT
Author: Arkadii Yakovets
Author-email: ark@cho.red
Requires-Python: >=3.8,<4.0
Classifier: License :: OSI Approved :: MIT License
Classifier: Programming Language :: Python :: 3
Classifier: Programming Language :: Python :: 3.8
Classifier: Programming Language :: Python :: 3.9
Classifier: Programming Language :: Python :: 3.10
Classifier: Programming Language :: Python :: 3.11
Classifier: Programming Language :: Python :: 3.12
